vtb_biname/__init__.py
vtb_biname/vtb_biname.py
vtb_biname-0.1.dist-info/METADATA
vtb_biname-0.1.dist-info/WHEEL
vtb_biname-0.1.dist-info/top_level.txt
vtb_biname-0.1.dist-info/RECORD
